gt_api/__init__.py
gt_api/challenge.py
gt_api/client.py
gt_api/errors.py
gt_api/generic.py
gt_api/geo.py
gt_api/highscore_hunt.py
gt_api/lobby.py
gt_api/login.py
gt_api/map.py
gt_api/matchmaking.py
gt_api/misc.py
gt_api/season.py
gt_api/settings.py
gt_api/user.py
gt_api-0.0.8.dist-info/licenses/LICENSE
gt_api-0.0.8.dist-info/METADATA
gt_api-0.0.8.dist-info/WHEEL
gt_api-0.0.8.dist-info/top_level.txt
gt_api-0.0.8.dist-info/RECORD
