Metadata-Version: 2.4
Name: gt_api
Version: 0.0.8
Summary: Geotastic internal API wrapper
Author-email: Adam Jenca <jenca.adam@gmail.com>
Maintainer-email: Adam Jenca <jenca.adam@gmail.com>
License:            DO WHAT THE FUCK YOU WANT TO PUBLIC LICENSE
Project-URL: Homepage, https://github.com/jenca-adam/geotastic_api
Project-URL: Bug Reports, https://github.com/jenca-adam/geotastic_api/issues
Project-URL: Source, https://github.com/jenca-adam/geotastic_api
Keywords: geotastic,api
Classifier: Development Status :: 3 - Alpha
Classifier: Programming Language :: Python :: 3 :: Only
Classifier: Topic :: Software Development :: Libraries :: Python Modules
Classifier: Intended Audience :: Developers
License-File: LICENSE
Requires-Dist: pycryptodome
Requires-Dist: requests
Requires-Dist: websockets
Dynamic: license-file
